pyinst/__init__.py
pyinst/__pyinstaller/__init__.py
pyinst/__pyinstaller/hook-pyinst.py
pyinst/abc.py
pyinst/constants.py
pyinst/deprecated.py
pyinst/DLLs/x64/ftd2xx.dll
pyinst/DLLs/x64/SiUSBXp.dll
pyinst/DLLs/x86/ftd2xx.dll
pyinst/DLLs/x86/SiUSBXp.dll
pyinst/errors.py
pyinst/functions.py
pyinst/libs/__init__.py
pyinst/libs/neo_usb_device.py
pyinst/models.py
pyinst/utils.py
pyinst-1.1.2.dist-info/entry_points.txt
pyinst-1.1.2.dist-info/METADATA
pyinst-1.1.2.dist-info/WHEEL
pyinst-1.1.2.dist-info/RECORD
