Metadata-Version: 2.1
Name: pyinst
Version: 1.1.2
Summary: 
Author: Chongjun Lei
Author-email: chongjun.lei@lumentum.com
Requires-Python: >=3.8.10,<4.0.0
Classifier: Programming Language :: Python :: 3
Classifier: Programming Language :: Python :: 3.9
Classifier: Programming Language :: Python :: 3.10
Classifier: Programming Language :: Python :: 3.11
Requires-Dist: PyVISA (>=1.12.0,<2.0.0)
Requires-Dist: ftd2xx (>=1.3.1,<2.0.0)
Requires-Dist: pyserial (>=3.5,<4.0)
